reljicd_utils/__init__.py
reljicd_utils/collections/__init__.py
reljicd_utils/collections/collections.py
reljicd_utils/collections/iter_counter.py
reljicd_utils/collections/iter_tools.py
reljicd_utils/config/__init__.py
reljicd_utils/config/env_vars.py
reljicd_utils/design_patterns/__init__.py
reljicd_utils/design_patterns/singleton.py
reljicd_utils/documents/__init__.py
reljicd_utils/documents/csv_processor.py
reljicd_utils/documents/excel.py
reljicd_utils/documents/xml.py
reljicd_utils/file_system/__init__.py
reljicd_utils/file_system/file_processor.py
reljicd_utils/file_system/file_system.py
reljicd_utils/logger/__init__.py
reljicd_utils/logger/logger.py
reljicd_utils/multiprocessing/__init__.py
reljicd_utils/multiprocessing/multiprocess.py
reljicd_utils/profiling/__init__.py
reljicd_utils/profiling/display_top.py
reljicd_utils/profiling/memory.py
reljicd_utils/profiling/time.py
reljicd_utils/rdbms/__init__.py
reljicd_utils/rdbms/base_model.py
reljicd_utils/rdbms/execute_sql_file.py
reljicd_utils/rdbms/recreate_database.py
reljicd_utils/rdbms/recreate_schema.py
reljicd_utils/rdbms/reindex_rds_indexes.py
reljicd_utils/rdbms/scoped_session.py
reljicd_utils/rdbms/session_scope.py
reljicd_utils/rdbms/set_sequences.py
reljicd_utils/rdbms/transaction.py
reljicd_utils/rdbms/utils.py
reljicd_utils/rdbms/vacuum_rds_schemas.py
reljicd_utils/utils/__init__.py
reljicd_utils/utils/date_time.py
reljicd_utils/utils/s3.py
reljicd_utils-0.0.4.dist-info/LICENSE
reljicd_utils-0.0.4.dist-info/METADATA
reljicd_utils-0.0.4.dist-info/WHEEL
reljicd_utils-0.0.4.dist-info/top_level.txt
reljicd_utils-0.0.4.dist-info/RECORD
